{
  "name": "Nettie Ortiz",
  "age": 57,
  "address": {
    "street": "Ujupel Park",
    "city": "Gisitwa",
    "state": "WA",
    "zip": "74023"
  },
  "contact": {
    "phone": "(734) 446-3093",
    "servicePhone": "800796389"
  },
  "birthday": "1986-04-24T05:28:38.760Z",
  "ip": "120.107.150.201",
  "foo": "bar",
  "profile": {
    "about": "Mawlir onhebgeg usuzif zun udceamo un tik zupme ju zeet ivicibu wid ucdoroh disnare fewu mo. Cuk vok pi fabbicag pojucru duaraza fenaz hadbapo voimdif fuasije urni nuhob mupawi kiviji aco. Pa oji ogihofez zo geudawe ci rifago jihceh rup zirirhid gifdujub top nu obe pi ej sijbi. Fori jetfejcam uk acoudsul lazew titobfol ubhubof nos famaj rem artavraz girazepu bir li. Reejlog ehe pumcildi uwu noj ce cet tiwvalre zuha ra horazes tisa. Is bonhizes birlaca jovduv otugaj joctazir recewilu wuz paggamoz dutibu lemofobez dokoji goboh abrehhi.",
    "bio": "Pifko jokkicdir ci sac iteaka nezi zal suzpu jowza jahdute jivu dibcaf vetbuw ogesob feksic iza. Uweda noulbon kirkom buwjow mazkuse raivagon puso gelre debuc agean rocidud detkiv aje cuhongo do ju umidecu la. Ale zuztodna jogaf hivokur fe fapu mupijric paravu wire aso dehporof zogkefa rutolaca ca penab adfi tek. Cevujov faprohze eda fo eh elibimco at kuris lurwol foehi ni giczahub nogowo jo. Wi zaftabzi oge be wulgosho waj sa wibweif sirmacu sorpawoh givurwaz ufezew fa cevmusuk."
  },
  "apiKey": "85c16dc40ac5abbec042c20c6c4891b08475863093ca0c5c2423f11d9f1f87df",
  "currency": {
    "code": "MZN",
    "name": "Mozambique Metical"
  }
}