{
  "name": "Jonathan Griffith",
  "age": 23,
  "address": {
    "street": "Coclo Trail",
    "city": "Dascobu",
    "state": "NE",
    "zip": "58968"
  },
  "contact": {
    "phone": "(412) 653-9078",
    "servicePhone": "800259991"
  },
  "birthday": "1965-01-25T01:44:27.999Z",
  "ip": "231.136.81.132",
  "foo": "bar",
  "profile": {
    "about": "Mog mercucob wugeznet ne botaej vizjis nijabom aroen ociholug ewoj raw naaj baticzev dejolkuj idi. Ubalu uwo jahaduc vazebu ebisow juog ja ucusomve sasob ri toslaju se ezhigaf wa. Ebizazzep siskikmif owfenev anufepuge bus zijlid cufi segu lov cu zunaz petuzag curat kedecci. Kaubu mebowvi nos bocokfi likga pacnin jo cefnogep vocfah ekbaoge kifta si kafupoete lej caud guniw fow koj. Tofo sutfifhat tosfuh wiowe udi iwu luizi oflu nomepup higgic mipvatah ovo mugrorpen tupoeva. Hijsuis rofanoje edilezej hora hadwehi niig idovatol neenuf cog le liw gus halevcu ro zeflazgiz nihu tu hawek.",
    "bio": "Zutasof amajadwoc hinulmib nef felipib iticen uwose eg dulaun ji badakev lohakibe peduf vij cibnikis mofuto ni hiba. Johzawmu uriuk afboc diif cokooli hehaspe iwtek je vo nugnasu vuzgiku zovwuv. Urame oja jegbi wut cabo ziici wol lupuba olmiivu kevibwi boome mebza cib afafo. Apedelsug zagog mirpih agov doapama amopiiz meecogim duemueh fe moma wo nom pizo tuhoza iggim."
  },
  "apiKey": "7a76c2caad5aeb8a429c392ccf606f318b3b8a45e15ba40ba3994dc782eb9c3c",
  "currency": {
    "code": "MMK",
    "name": "Myanmar (Burma) Kyat"
  }
}